{
    "create_time": "2019-04-10 15-31-45",
    "start_time": "2019-04-10 14-00",
    "end_time": "\u672a\u8bbe\u7f6e",
    "interval": 30,
    "step": 2,
    "points": {
        "center_point": [
            25.878994,
            117.839355
        ],
        "north_west_point": [
            28.262763,
            115.330077
        ],
        "north_east_point": [
            28.262763,
            120.383787
        ],
        "south_east_point": [
            23.442771,
            120.383787
        ],
        "south_west_point": [
            23.442771,
            115.330077
        ]
    },
    "save_file_dir": "D:\\mycode\\CrawlerRadarPrecipitationMap\\tmp",
    "remark": "\u798f\u5efa\u7701\u96f7\u8fbe\u964d\u6c34\u56fe",
    "extent_gcj02": [
        23.442771,
        115.330077,
        28.262763,
        120.383787
    ],
    "project_dir": "D:\\mycode\\CrawlerRadarPrecipitationMap\\tmp\\2019-04-10 15-31-45",
    "log_dir": "D:\\mycode\\CrawlerRadarPrecipitationMap\\tmp\\2019-04-10 15-31-45\\log"
}